just_agents/coding/__init__.py
just_agents/coding/tools.py
just_agents_coding-0.8.7.dist-info/METADATA
just_agents_coding-0.8.7.dist-info/WHEEL
just_agents_coding-0.8.7.dist-info/RECORD
