Metadata-Version: 2.4
Name: just-agents-coding
Version: 0.8.7
Summary: Just Agents - Coding Components
License: MIT
Author: Alex Karmazin
Author-email: karmazinalex@gmail.com
Maintainer: Anton Kulaga
Maintainer-email: antonkulaga@gmail.com
Requires-Python: >=3.10,<3.15
Classifier: License :: OSI Approved :: MIT License
Classifier: Programming Language :: Python :: 3
Classifier: Programming Language :: Python :: 3.10
Classifier: Programming Language :: Python :: 3.11
Classifier: Programming Language :: Python :: 3.12
Classifier: Programming Language :: Python :: 3.13
Classifier: Programming Language :: Python :: 3.14
Requires-Dist: docker (>=7.1.0)
Requires-Dist: just-agents-core
Requires-Dist: llm-sandbox[podman] (>=0.3.4)
Requires-Dist: requests (>=2.32.3)
